pisat/__init__.py
pisat/temp.py
pisat/actuator/__init__.py
pisat/actuator/bd62xx.py
pisat/actuator/param_cushion.py
pisat/actuator/pwm_dc_motor_driver.py
pisat/actuator/rotate_motor_driver_base.py
pisat/actuator/servo_motor_base.py
pisat/actuator/two_wheels.py
pisat/actuator/vref_dc_motor_driver_base.py
pisat/base/__init__.py
pisat/base/component.py
pisat/base/component_group.py
pisat/calc/__init__.py
pisat/calc/altitude.py
pisat/calc/navigator.py
pisat/calc/position.py
pisat/comm/__init__.py
pisat/comm/formatter/__init__.py
pisat/comm/transceiver/__init__.py
pisat/comm/transceiver/comm_socket.py
pisat/comm/transceiver/comm_stream.py
pisat/comm/transceiver/command_server.py
pisat/comm/transceiver/im920.py
pisat/comm/transceiver/im920s.py
pisat/comm/transceiver/request.py
pisat/comm/transceiver/socket_transceiver.py
pisat/comm/transceiver/transceiver_base.py
pisat/core/__init__.py
pisat/core/cansat/__init__.py
pisat/core/cansat/cansat.py
pisat/core/logger/__init__.py
pisat/core/logger/datalogger.py
pisat/core/logger/logque.py
pisat/core/logger/refque.py
pisat/core/logger/systemlogger.py
pisat/core/manager/__init__.py
pisat/core/manager/component_manager.py
pisat/core/nav/__init__.py
pisat/core/nav/context.py
pisat/core/nav/node.py
pisat/core/nav/post_event.py
pisat/handler/__init__.py
pisat/handler/digital_input_handler_base.py
pisat/handler/digital_io_handler_base.py
pisat/handler/digital_output_handler_base.py
pisat/handler/handler_base.py
pisat/handler/handler_helper.py
pisat/handler/i2c_handler_base.py
pisat/handler/pigpio_digital_input_handler.py
pisat/handler/pigpio_digital_output_handler.py
pisat/handler/pigpio_i2c_handler.py
pisat/handler/pigpio_pwm_handler.py
pisat/handler/pigpio_serial_handler.py
pisat/handler/pigpio_spi_handler.py
pisat/handler/pwm_handler_base.py
pisat/handler/pyserial_serial_handler.py
pisat/handler/rpigpio_digital_input_handler.py
pisat/handler/rpigpio_digital_output_handler.py
pisat/handler/rpigpio_pwm_handler.py
pisat-0.0.0.dist-info/LICENSE
pisat-0.0.0.dist-info/METADATA
pisat-0.0.0.dist-info/WHEEL
pisat-0.0.0.dist-info/top_level.txt
pisat-0.0.0.dist-info/RECORD
