Metadata-Version: 2.1
Name: pisat
Version: 0.0.0
Summary: Python Robot and IoT framework with state-management.
Home-page: https://github.com/jjj999/pisat/
Author: Yunhyeon Jeong
Author-email: jjj999to@gmail.com
License: UNKNOWN
Platform: UNKNOWN
Requires-Python: >=3.7
